arithpack/__init__.py
arithpack-0.1.0.dist-info/licenses/LICENSE
arithpack-0.1.0.dist-info/METADATA
arithpack-0.1.0.dist-info/WHEEL
arithpack-0.1.0.dist-info/top_level.txt
arithpack-0.1.0.dist-info/RECORD
