Metadata-Version: 2.4
Name: arithpack
Version: 0.1.0
Summary: A simple arithmetic operations package
Author-email: Your Name <you@example.com>
Project-URL: Homepage, https://example.com/arithpack
Requires-Python: >=3.7
License-File: LICENSE
Dynamic: license-file
